[
    {
        "sender": "Ab",
        "text": "fdsa",
        "date": "fdas"
    },
    {
        "sender": "fads",
        "text": "fads",
        "date": "fsdafsad"
    },
    {
        "sender": "fads",
        "text": "fads",
        "date": "fsdafsad"
    },
    {
        "sender": "fads",
        "text": "fads",
        "date": "fsdafsad"
    },
    {
        "sender": "Бахром",
        "text": "dfdasd",
        "date": "13:44"
    },
    {
        "sender": "Бахром",
        "text": "dfdasd",
        "date": "13:44"
    },
    {
        "sender": "Бахром",
        "text": "dfdasd",
        "date": "13:44"
    },
    {
        "sender": "Бахром",
        "text": "dfdasd",
        "date": "13:44"
    },
    {
        "sender": "Бахром",
        "text": "fasd",
        "date": "13:44"
    },
    {
        "sender": "Бахром",
        "text": "fasd",
        "date": "13:44"
    },
    {
        "sender": "Бахром",
        "text": "fdas",
        "date": "13:45"
    },
    {
        "sender": "Бахром",
        "text": "fds",
        "date": "13:46"
    },
    {
        "sender": "Бахром",
        "text": "fds",
        "date": "13:46"
    },
    {
        "sender": "Бахром",
        "text": "fsd",
        "date": "13:46"
    },
    {
        "sender": "Бахром",
        "text": "fds",
        "date": "13:46"
    },
    {
        "sender": "Бахром",
        "text": "fd",
        "date": "13:46"
    },
    {
        "sender": "Бахром",
        "text": "afd",
        "date": "13:46"
    },
    {
        "sender": "Бахром",
        "text": "fds",
        "date": "13:46"
    },
    {
        "sender": "Бахром",
        "text": "afsd",
        "date": "13:46"
    },
    {
        "sender": "Бахром",
        "text": "fdas",
        "date": "13:46"
    },
    {
        "sender": "Бахром",
        "text": "afsd",
        "date": "13:46"
    },
    {
        "sender": "Бахром",
        "text": "dsa",
        "date": "13:47"
    },
    {
        "sender": "Бахром",
        "text": "gsf",
        "date": "13:48"
    }
]